hg_number.py
hg_number-0.0.5.dist-info/WHEEL
hg_number-0.0.5.dist-info/METADATA
hg_number-0.0.5.dist-info/DESCRIPTION.rst
hg_number-0.0.5.dist-info/RECORD
hg_number-0.0.5.dist-info/pbr.json
hg_number-0.0.5.dist-info/entry_points.txt
hg_number-0.0.5.dist-info/top_level.txt
hg_number-0.0.5.dist-info/metadata.json
