Metadata-Version: 2.0
Name: hg-number
Version: 0.0.5
Summary: a python script that allows you to use numbers instead of file names in mercurial commands
Home-page: https://github.com/gsingh93/hg-number
Author: Gulshan Singh
Author-email: gsingh2011@gmail.com
License: MIT
Keywords: hg mercurial vcs
Platform: UNKNOWN
Classifier: Development Status :: 4 - Beta
Classifier: Intended Audience :: Developers
Classifier: License :: OSI Approved :: MIT License
Classifier: Programming Language :: Python :: 2
Classifier: Programming Language :: Python :: 2.6
Classifier: Programming Language :: Python :: 2.7
Requires-Dist: termcolor
